adif2callhistory/__init__.py
adif2callhistory/__main__.py
adif2callhistory/main.ui
adif2callhistory-25.3.17.dist-info/LICENSE
adif2callhistory-25.3.17.dist-info/METADATA
adif2callhistory-25.3.17.dist-info/WHEEL
adif2callhistory-25.3.17.dist-info/entry_points.txt
adif2callhistory-25.3.17.dist-info/top_level.txt
adif2callhistory-25.3.17.dist-info/RECORD
